binance_fix_connector/__init__.py
binance_fix_connector/fix_connector.py
binance_fix_connector/utils.py
binance_fix_connector-1.0.1.dist-info/licenses/LICENSE
binance_fix_connector-1.0.1.dist-info/METADATA
binance_fix_connector-1.0.1.dist-info/WHEEL
binance_fix_connector-1.0.1.dist-info/top_level.txt
binance_fix_connector-1.0.1.dist-info/RECORD
