Metadata-Version: 2.4
Name: binance_fix_connector
Version: 1.0.1
Summary: This is a simple Python library that provides access to Binance Financial Information eXchange (FIX) SPOT messages using the FIX protocol.
Author: Binance
License: MIT License
Keywords: binance,fix,connector
Classifier: Intended Audience :: Developers
Classifier: Intended Audience :: Financial and Insurance Industry
Classifier: License :: OSI Approved :: MIT License
Classifier: Programming Language :: Python :: 3.9
Classifier: Programming Language :: Python :: 3.10
Classifier: Programming Language :: Python :: 3.11
Classifier: Programming Language :: Python :: 3.12
Classifier: Programming Language :: Python :: 3.13
Requires-Python: >=3.9
License-File: LICENSE
Requires-Dist: simplefix
Requires-Dist: cryptography
Requires-Dist: black
Dynamic: license-file
